handoff/__init__.py
handoff/config.py
handoff/main.py
handoff/core/__init__.py
handoff/core/admin.py
handoff/core/operators.py
handoff/core/project_schema.json
handoff/core/task.py
handoff/plugins/__init__.py
handoff/plugins/envs/__init__.py
handoff/plugins/quick_start/__init__.py
handoff/services/__init__.py
handoff/services/cloud/__init__.py
handoff/services/cloud/aws/__init__.py
handoff/services/cloud/aws/cloudformation.py
handoff/services/cloud/aws/credentials.py
handoff/services/cloud/aws/ecr.py
handoff/services/cloud/aws/ecs.py
handoff/services/cloud/aws/events.py
handoff/services/cloud/aws/iam.py
handoff/services/cloud/aws/logs.py
handoff/services/cloud/aws/s3.py
handoff/services/cloud/aws/ssm.py
handoff/services/cloud/aws/stepfunctions.py
handoff/services/cloud/aws/sts.py
handoff/services/cloud/aws/cloudformation_templates/alarm.yml
handoff/services/cloud/aws/cloudformation_templates/resources.yml
handoff/services/cloud/aws/cloudformation_templates/resources_static_ip.yml
handoff/services/cloud/aws/cloudformation_templates/role.yml
handoff/services/cloud/aws/cloudformation_templates/s3.yml
handoff/services/cloud/aws/cloudformation_templates/task.yml
handoff/services/container/__init__.py
handoff/services/container/docker/Dockerfile
handoff/services/container/docker/__init__.py
handoff/services/container/docker/impl.py
handoff/services/container/docker/script/install_handoff
handoff/services/github/__init__.py
handoff/test_projects/start
handoff/test_projects/01_word_count/project.yml
handoff/test_projects/01_word_count/files/the_great_dictator_speech.txt
handoff/test_projects/02_commands_and_vars/project.yml
handoff/test_projects/02_commands_and_vars/files/the_great_dictator_speech.txt
handoff/test_projects/03_secrets/project.yml
handoff/test_projects/03_secrets/.secrets/google_client_secret.json
handoff/test_projects/03_secrets/.secrets/secrets.yml
handoff/test_projects/03_secrets/files/config.json
handoff-0.4.2.dist-info/licenses/AUTHORS.md
handoff-0.4.2.dist-info/licenses/LICENSE
handoff-0.4.2.dist-info/METADATA
handoff-0.4.2.dist-info/WHEEL
handoff-0.4.2.dist-info/entry_points.txt
handoff-0.4.2.dist-info/top_level.txt
handoff-0.4.2.dist-info/RECORD
