Metadata-Version: 2.4
Name: handoff
Version: 0.4.2
Summary: Deploy configurable unix pipeline jobs serverlessly.
Author: Daigo Tanaka
License-Expression: Apache-2.0
Project-URL: Homepage, https://handoff.cloud
Project-URL: Documentation, https://dev.handoff.cloud
Classifier: Development Status :: 4 - Beta
Classifier: Operating System :: MacOS :: MacOS X
Classifier: Operating System :: POSIX :: Linux
Classifier: Programming Language :: Python :: 3.9
Classifier: Programming Language :: Python :: 3.10
Classifier: Programming Language :: Python :: 3.11
Classifier: Programming Language :: Python :: 3.12
Requires-Python: >=3.9
License-File: LICENSE
License-File: AUTHORS.md
Requires-Dist: attrs==25.3.0
Requires-Dist: boto3==1.40.22
Requires-Dist: botocore==1.40.22
Requires-Dist: docker==7.1.0
Requires-Dist: jinja2==3.1.6
Requires-Dist: jsonschema==4.25.1
Requires-Dist: lxml==6.0.1
Requires-Dist: packaging==25.0
Requires-Dist: psutil==7.0.0
Requires-Dist: pygit2==1.13.0
Requires-Dist: pygithub==1.59.1
Requires-Dist: python-dateutil==2.9.0.post0
Requires-Dist: pyyaml==6.0.2
Requires-Dist: requests==2.32.5
Requires-Dist: s3transfer==0.13.1
Dynamic: license-file
